{"id": 13497269, "user_id": 10150369, "name": "Iceland", "type": null, "visibility": 1, "slug": "iceland", "start_date": 1724306400.0, "end_date": 1724911199.0, "is_deleted": false, "open_graph_id": null, "fb_publish_status": null, "total_km": 725.7084511245073, "views": 24, "featured": null, "featured_priority_for_new_users": null, "feature_text": null, "feature_date": null, "language": null, "timezone_id": "America/Denver", "summary": "The land of fire and ice\u2026 and waterfalls!", "cover_photo_path": "https://polarsteps.s3.amazonaws.com/user_images/steps/large_thumb/u_10150369/B5FF2DD3-80E9-4A6A-BD7B-F37857687AF8_863870CE-AF20-4929-B154-8906F5F38D8C.jpg", "cover_photo_thumb_path": "https://polarsteps.s3.amazonaws.com/user_images/steps/small_thumb/u_10150369/B5FF2DD3-80E9-4A6A-BD7B-F37857687AF8_0A7375B4-6016-4100-9F69-2F67616F6675.jpg", "cover_photo": {"id": 9274201, "path": "https://polarsteps.s3.amazonaws.com/user_images/steps/full_res/u_10150369/B5FF2DD3-80E9-4A6A-BD7B-F37857687AF8_02F9C536-106A-4E5E-A02B-2B3502CBDDE4.jpg", "large_thumbnail_path": "https://polarsteps.s3.amazonaws.com/user_images/steps/large_thumb/u_10150369/B5FF2DD3-80E9-4A6A-BD7B-F37857687AF8_863870CE-AF20-4929-B154-8906F5F38D8C.jpg", "small_thumbnail_path": "https://polarsteps.s3.amazonaws.com/user_images/steps/small_thumb/u_10150369/B5FF2DD3-80E9-4A6A-BD7B-F37857687AF8_0A7375B4-6016-4100-9F69-2F67616F6675.jpg", "type": 0, "media_id": 918878714, "trip_id": 13497269, "full_res_unavailable": false, "last_modified": 1724539108.291111, "uuid": "EA8A3533-DB1F-4511-9D84-64448BE4FE87"}, "planned_steps_visible": true, "future_timeline_last_modified": 1724568564.448, "creation_time": 1724846456.521779, "step_count": 22, "travel_tracker_device": {"id": 7170577, "trip_id": 13497269, "device_name": null, "tracking_status": 0, "uuid": "1cf32e0e-6d29-441d-9644-248fe170902e"}, "uuid": "210A2F46-5AAA-4BDB-B7B7-DA2E976D1CE2", "all_steps": [{"id": 120782300, "trip_id": 13497269, "location_id": 149407542, "main_media_item_path": null, "name": "Reykjavik", "display_name": "Reykjavik", "description": "We are off the boat! And with a rental car we are free to explore this beautiful country!", "slug": "reykjavik", "display_slug": "reykjavik", "type": 1, "start_time": 1724313600.0, "end_time": null, "creation_time": 1724534050.692526, "location": {"id": 149407542, "name": "Reykjavik", "detail": "Iceland", "full_detail": "Capital Region, Iceland", "country_code": "IS", "lat": 64.14598099999999, "lon": -21.942236699999995, "venue": null, "uuid": "731D0C69-7DA8-42B8-B3EB-4DCD7606FF5F"}, "supertype": "normal", "is_deleted": false, "open_graph_id": null, "fb_publish_status": null, "timezone_id": "Atlantic/Reykjavik", "views": 0, "comment_count": 0, "weather_condition": "wind", "weather_temperature": 10.0, "uuid": "A9A7C165-2195-4FD5-BA4D-39A5C9E0528E"}, {"id": 120783356, "trip_id": 13497269, "location_id": 149408762, "main_media_item_path": null, "name": "Glymur Waterfall", "display_name": "Glymur Waterfall", "description": "Glymur waterfall is a spectacular hike! We saw Icelandic sheep up close, walked through a cave, crossed a river, and saw magnificent views of the second tallest waterfall in Iceland cascading into a narrow canyon.", "slug": "capital-region", "display_slug": "capital-region", "type": 1, "start_time": 1724320800.0, "end_time": null, "creation_time": 1724534479.694978, "location": {"id": 149408762, "name": "Capital Region", "detail": "Iceland", "full_detail": "Capital Region, Iceland", "country_code": "IS", "lat": 64.38573837933139, "lon": -21.233552309421214, "venue": null, "uuid": "1A7294FD-5506-4EF4-9D4F-04C84D2A1EA1"}, "supertype": "normal", "is_deleted": false, "open_graph_id": null, "fb_publish_status": null, "timezone_id": "Atlantic/Reykjavik", "views": 0, "comment_count": 0, "weather_condition": "rain", "weather_temperature": 10.0, "uuid": "FEFA627E-B083-4B41-A1E2-FEF033812FEA"}, {"id": 120784006, "trip_id": 13497269, "location_id": 149409544, "main_media_item_path": null, "name": "Mid Atlantic Ridge", "display_name": "Mid Atlantic Ridge", "description": "Iceland sits on the Mid Atlantic Ridge. This is where the Eurasian tectonic plate and the North American tectonic plate are diverging. This is how Iceland is formed, why it is such a new (geologically) island, so volcanic and geothermal activity, and why it is growing bigger each year!", "slug": "southern-region", "display_slug": "southern-region", "type": 1, "start_time": 1724328000.0, "end_time": null, "creation_time": 1724534805.258126, "location": {"id": 149409544, "name": "Southern Region", "detail": "Iceland", "full_detail": "Iceland", "country_code": "IS", "lat": 64.25174512514484, "lon": -21.110565319489893, "venue": null, "uuid": "D8155F61-EC0A-4576-B5EB-861B24AE005D"}, "supertype": "normal", "is_deleted": false, "open_graph_id": null, "fb_publish_status": null, "timezone_id": "Atlantic/Reykjavik", "views": 0, "comment_count": 0, "weather_condition": "rain", "weather_temperature": 10.0, "uuid": "6832982D-D149-4075-879D-3727E93A9592"}, {"id": 120785650, "trip_id": 13497269, "location_id": 149411480, "main_media_item_path": null, "name": "Cottage", "display_name": "Cottage", "description": "Our AirBnb is this cute little cabin off a dirt road in a remote area. We drive over a cute narrow bridge to get here. The house had toys from their kids, it was just what Harvey and Fran needed \u2014 a quiet evening just playing toys in a house. I went down the hill and took pictures of the Icelandic horses! They are so cute!\n\nIcelandic horses were brought to Iceland by the Norse in the 9th century. They are a special breed of horses that is smaller, almost pony sized, and have lots of hair. These horses are really important to Icelandic culture, so no other horses are allowed in the country or out of the country to keep them distinct and isolated.\n\nOh, and the volcano about 80 miles away is erupting right now.", "slug": "south", "display_slug": "south", "type": 1, "start_time": 1724353200.0, "end_time": null, "creation_time": 1724535611.881363, "location": {"id": 149411480, "name": "South", "detail": "Iceland", "full_detail": "South, Iceland", "country_code": "IS", "lat": 64.26070094385939, "lon": -20.30585812751667, "venue": null, "uuid": "B415CE7C-F897-4D3E-A383-3B76F9998D2F"}, "supertype": "normal", "is_deleted": false, "open_graph_id": null, "fb_publish_status": null, "timezone_id": "Atlantic/Reykjavik", "views": 0, "comment_count": 0, "weather_condition": "rain", "weather_temperature": 10.0, "uuid": "E5938C8A-3013-4E43-857D-F524112543FA"}, {"id": 120786226, "trip_id": 13497269, "location_id": 149412164, "main_media_item_path": null, "name": "Secret Lagoon", "display_name": "Secret Lagoon", "description": "Icelanders are known for the obsession with swimming pools. This morning we went to the Secret Lagoon, the oldest natural pool in Iceland. It is heated by the geysers that surround the pool. It was so lovely!", "slug": "south", "display_slug": "south", "type": 1, "start_time": 1724407200.0, "end_time": null, "creation_time": 1724535923.936529, "location": {"id": 149412164, "name": "South", "detail": "Iceland", "full_detail": "South, Iceland", "country_code": "IS", "lat": 64.1592529708336, "lon": -20.325866524259, "venue": null, "uuid": "A105AE11-44C3-482C-886C-A2130FC84344"}, "supertype": "normal", "is_deleted": false, "open_graph_id": null, "fb_publish_status": null, "timezone_id": "Atlantic/Reykjavik", "views": 0, "comment_count": 0, "weather_condition": "rain", "weather_temperature": 9.0, "uuid": "DA95605E-AEAD-49AB-AD41-904A97B42633"}, {"id": 120786816, "trip_id": 13497269, "location_id": 149412833, "main_media_item_path": null, "name": "Gullfoss ", "display_name": "Gullfoss ", "description": "Gullfoss (translated to \u2018Golden Falls\u2019) is one of Iceland\u2019s most iconic waterfalls. The water in Hv\u00edt\u00e1 river travels from the glacier Langj\u00f6kull, before cascading 105 feet down in two stages into a narrow canyon.", "slug": "southern-region", "display_slug": "southern-region", "type": 1, "start_time": 1724425200.0, "end_time": null, "creation_time": 1724536220.425472, "location": {"id": 149412833, "name": "Southern Region", "detail": "Iceland", "full_detail": "Iceland", "country_code": "IS", "lat": 64.30943467691391, "lon": -20.153087668553553, "venue": null, "uuid": "79BE06E1-3B8B-469F-988D-622381D21CD5"}, "supertype": "normal", "is_deleted": false, "open_graph_id": null, "fb_publish_status": null, "timezone_id": "Atlantic/Reykjavik", "views": 0, "comment_count": 1, "weather_condition": "cloudy", "weather_temperature": 7.0, "uuid": "F58218D4-D67D-42EE-9C18-3D3C19BAA494"}, {"id": 120787756, "trip_id": 13497269, "location_id": 149413960, "main_media_item_path": null, "name": "Geysir", "display_name": "Geysir", "description": "Iceland has a lot of geothermal activity. Geysir is one of the largest in the world, spouting water 200 feet into the air, although isn\u2019t very active lately. This is were the term geyser comes from. Strokkur is active, spouting water every 5-10 minutes about 50 feet into the air. \n\nMy hand almost froze off trying to get pictures of this one! It was so cold and windy out. Did you know Iceland is one of the windiest places on land in the world?\n\n", "slug": "south", "display_slug": "south", "type": 1, "start_time": 1724436000.0, "end_time": null, "creation_time": 1724536241.931803, "location": {"id": 149413960, "name": "South", "detail": "Iceland", "full_detail": "South, Iceland", "country_code": "IS", "lat": 64.30967673582418, "lon": -20.235263013826057, "venue": null, "uuid": "3C5A5F0D-B0E4-4029-B6A6-328E9B7B264A"}, "supertype": "normal", "is_deleted": false, "open_graph_id": null, "fb_publish_status": null, "timezone_id": "Atlantic/Reykjavik", "views": 0, "comment_count": 0, "weather_condition": "rain", "weather_temperature": 8.0, "uuid": "06BDF336-F7CB-47C4-83BF-35ADF1FA5F9B"}, {"id": 120788425, "trip_id": 13497269, "location_id": 149414754, "main_media_item_path": null, "name": "Farms", "display_name": "Farms", "description": "For dinner we ate at Efstidalur, a local family owned farm that specializes in Farm to Table cuisine. They had viewing windows of the cows eating right in the restaurant! Not sure if we have had so fresh and local of a hamburger, milk, and ice cream before!\n\nLike the Icelandic horses, Icelandic cattle and chickens were brought over by the Norse in the 9th century and have been genetically isolated for a thousand years.\n", "slug": "south", "display_slug": "south", "type": 1, "start_time": 1724439600.0, "end_time": null, "creation_time": 1724537166.779354, "location": {"id": 149414754, "name": "South", "detail": "Iceland", "full_detail": "South, Iceland", "country_code": "IS", "lat": 64.30818978226463, "lon": -20.30712384950914, "venue": null, "uuid": "8CA07468-547D-4434-AFBA-6928ECA52F72"}, "supertype": "normal", "is_deleted": false, "open_graph_id": null, "fb_publish_status": null, "timezone_id": "Atlantic/Reykjavik", "views": 0, "comment_count": 2, "weather_condition": "rain", "weather_temperature": 9.0, "uuid": "7FAC3E40-33C9-4033-B4A7-2C4D49839C42"}, {"id": 120788724, "trip_id": 13497269, "location_id": 149415102, "main_media_item_path": null, "name": "Br\u00faarfoss", "display_name": "Br\u00faarfoss", "description": "Br\u00faarfoss is considered Iceland\u2019s blueist waterfall!", "slug": "southern-region", "display_slug": "southern-region", "type": 1, "start_time": 1724443200.0, "end_time": null, "creation_time": 1724537367.800737, "location": {"id": 149415102, "name": "Southern Region", "detail": "Iceland", "full_detail": "Iceland", "country_code": "IS", "lat": 64.31239598596396, "lon": -20.296530894701363, "venue": null, "uuid": "25C8C5FE-9860-45F1-A1E9-356D943F6BCA"}, "supertype": "normal", "is_deleted": false, "open_graph_id": null, "fb_publish_status": null, "timezone_id": "Atlantic/Reykjavik", "views": 0, "comment_count": 1, "weather_condition": "rain", "weather_temperature": 9.0, "uuid": "857392EB-0937-42C0-9E1A-8260B2B7BFEF"}, {"id": 120790213, "trip_id": 13497269, "location_id": 149416924, "main_media_item_path": null, "name": "Landmannalaugar", "display_name": "Landmannalaugar", "description": "Today we went hiking at Landmannalaugar in the highlands. We had a take a rough dirt road to get to this remote location, but it was so worth it. It was so beautiful. It is in a lava field from an eruption in 1477. We hiked to the top of  Bl\u00e1hnj\u00fakur (blue mountain). The area was so colorful and unique. Like everywhere else, pictures don\u2019t do it justice. We loved this hike and the kids rocked it! Definitely the youngest ones out there. But we drastically messed up the lunch situation and were all starving!", "slug": "landmannalaugar", "display_slug": "landmannalaugar", "type": 1, "start_time": 1724493600.0, "end_time": null, "creation_time": 1724538388.487132, "location": {"id": 149416924, "name": "South", "detail": "Iceland", "full_detail": "South, Iceland", "country_code": "IS", "lat": 63.912606221121365, "lon": -19.059972121352104, "venue": null, "uuid": "B6F12D68-AAB5-4E09-AA77-F553B034B4CF"}, "supertype": "normal", "is_deleted": false, "open_graph_id": null, "fb_publish_status": null, "timezone_id": "Atlantic/Reykjavik", "views": 0, "comment_count": 0, "weather_condition": "partly-cloudy-day", "weather_temperature": 6.0, "uuid": "12139b88-8d9e-47c1-b7ee-dbc047dab0f2"}, {"id": 120790418, "trip_id": 13497269, "location_id": 149417168, "main_media_item_path": null, "name": "Lj\u00f3tipollur", "display_name": "Lj\u00f3tipollur", "description": "Lj\u00f3tipollur (ugly puddle) is a beautiful crater lake.", "slug": "green-backbone", "display_slug": "green-backbone", "type": 1, "start_time": 1724508000.0, "end_time": null, "creation_time": 1724538561.160192, "location": {"id": 149417168, "name": "Green Backbone", "detail": "Iceland", "full_detail": "Green Backbone, Iceland", "country_code": "IS", "lat": 63.9304932866376, "lon": -19.014959012420036, "venue": null, "uuid": "156D98BE-7C93-43CE-8786-328740E4FF70"}, "supertype": "normal", "is_deleted": false, "open_graph_id": null, "fb_publish_status": null, "timezone_id": "Atlantic/Reykjavik", "views": 0, "comment_count": 0, "weather_condition": "partly-cloudy-day", "weather_temperature": 5.0, "uuid": "D8AB1074-060D-4DF6-AE7D-EAA813C1E480"}, {"id": 120791009, "trip_id": 13497269, "location_id": 149417919, "main_media_item_path": null, "name": "Sig\u00f6ldufoss", "display_name": "Sig\u00f6ldufoss", "description": "", "slug": "south", "display_slug": "south", "type": 1, "start_time": 1724517000.0, "end_time": null, "creation_time": 1724539026.501067, "location": {"id": 149417919, "name": "South", "detail": "Iceland", "full_detail": "South, Iceland", "country_code": "IS", "lat": 64.1953179754545, "lon": -19.091630756975945, "venue": null, "uuid": "0082163B-4619-42B8-A377-4557C0665672"}, "supertype": "normal", "is_deleted": false, "open_graph_id": null, "fb_publish_status": null, "timezone_id": "Atlantic/Reykjavik", "views": 0, "comment_count": 0, "weather_condition": "rain", "weather_temperature": 4.0, "uuid": "56AE8D58-6091-4D51-BAAC-103B3DFA726C"}, {"id": 121319316, "trip_id": 13497269, "location_id": 150072909, "main_media_item_path": null, "name": "\u00c6rslabelgur", "display_name": "\u00c6rslabelgur", "description": "Even with a long day of hiking and meal time long past due, when you see a \u00c6rslabelgur pillow jumper, you\u2019ve got to pull over and jump!", "slug": "south", "display_slug": "south", "type": 1, "start_time": 1724526900.0, "end_time": null, "creation_time": 1724799392.166337, "location": {"id": 150072909, "name": "South", "detail": "Iceland", "full_detail": "South, Iceland", "country_code": "IS", "lat": 64.19863166786853, "lon": -20.246049590908882, "venue": null, "uuid": "E0F13287-F95B-49DF-8D36-D91B73C031F1"}, "supertype": "normal", "is_deleted": false, "open_graph_id": null, "fb_publish_status": null, "timezone_id": "Atlantic/Reykjavik", "views": 0, "comment_count": 0, "weather_condition": "partly-cloudy-day", "weather_temperature": 11.0, "uuid": "1D7AA00B-125C-44D3-B433-99207E28C547"}, {"id": 121319154, "trip_id": 13497269, "location_id": 150072731, "main_media_item_path": null, "name": "Selfoss Branch", "display_name": "Selfoss Branch", "description": "We attended church at the Selfoss Branch. After two weeks of \u201cchurch on boat\u201d it was great to go to church again. Even if it was in Icelandic! ", "slug": "selfoss", "display_slug": "selfoss", "type": 1, "start_time": 1724580000.0, "end_time": null, "creation_time": 1724799235.888738, "location": {"id": 150072731, "name": "Selfoss", "detail": "Iceland", "full_detail": "South, Iceland", "country_code": "IS", "lat": 63.93699356998004, "lon": -21.01099153280802, "venue": null, "uuid": "EA5AB3B6-FDD5-4E2E-BBC3-AF84157FCD96"}, "supertype": "normal", "is_deleted": false, "open_graph_id": null, "fb_publish_status": null, "timezone_id": "Atlantic/Reykjavik", "views": 0, "comment_count": 0, "weather_condition": "partly-cloudy-day", "weather_temperature": 11.0, "uuid": "E2589DE4-6FEC-40E1-A0BA-13768918984B"}, {"id": 121319749, "trip_id": 13497269, "location_id": 150073434, "main_media_item_path": null, "name": "Dyrh\u00f3laey", "display_name": "Dyrh\u00f3laey", "description": "Great overlook with a lighthouse, jagged cliffs and arches, and views of the glacier and beach.\n\nAnd we saw PUFFINS!!! Most are done nesting and have moved on, so we were really lucky to see the few that we did. And we saw a whale and some seals! Lots of fulmer birds.", "slug": "southern-region", "display_slug": "southern-region", "type": 1, "start_time": 1724594400.0, "end_time": null, "creation_time": 1724799935.608391, "location": {"id": 150073434, "name": "Southern Region", "detail": "Iceland", "full_detail": "Iceland", "country_code": "IS", "lat": 63.39983792030967, "lon": -19.12469136934226, "venue": null, "uuid": "9558B5A6-C243-4F37-B862-FD9D4627B2F2"}, "supertype": "normal", "is_deleted": false, "open_graph_id": null, "fb_publish_status": null, "timezone_id": "Atlantic/Reykjavik", "views": 0, "comment_count": 0, "weather_condition": "partly-cloudy-day", "weather_temperature": 11.0, "uuid": "1FC58FF6-EF95-4C96-8E87-36C4E07BFA63"}, {"id": 121320095, "trip_id": 13497269, "location_id": 150073875, "main_media_item_path": null, "name": "Black Sand beach", "display_name": "Black Sand beach", "description": "The kids were so excited to dig on a beach. And this beach is like no other. Black sand, no sea shells, just lava rocks, and basalt columns.", "slug": "iceland", "display_slug": "iceland", "type": 1, "start_time": 1724598000.0, "end_time": null, "creation_time": 1724800406.126169, "location": {"id": 150073875, "name": "Iceland", "detail": "Iceland", "full_detail": "Iceland", "country_code": "IS", "lat": 63.404771600923354, "lon": -19.053102667518573, "venue": null, "uuid": "EE68F4B0-8612-453E-B8EA-3F879F5B736A"}, "supertype": "normal", "is_deleted": false, "open_graph_id": null, "fb_publish_status": null, "timezone_id": "Atlantic/Reykjavik", "views": 0, "comment_count": 0, "weather_condition": "partly-cloudy-day", "weather_temperature": 11.0, "uuid": "7CC4B318-35BF-49C3-A226-C2264AFB2B08"}, {"id": 121320909, "trip_id": 13497269, "location_id": 150074827, "main_media_item_path": null, "name": "Fimmv\u00f6r\u00f0uh\u00e1ls", "display_name": "Fimmv\u00f6r\u00f0uh\u00e1ls", "description": "Today Harvey and I hiked Fimmv\u00f6r\u00f0uh\u00e1ls. This epic hike was 25km (15.5mi) and had 1400m (4600ft) elevation gain. We rocked it by finishing in 7hrs 22min (6hrs 44min moving time).\n\nWe saw 25+ waterfalls, crossed a glacier, passed though recent lava flows, saw gorgeous mountain views, and a vibrant landscape of colorful vegetation.\n\nWe even saw an artic fox up close!!\n\nFran and Robbie had an adventure picking us up. We didn\u2019t realize that road involved 13 river crossings!", "slug": "southern-region", "display_slug": "southern-region", "type": 1, "start_time": 1724666400.0, "end_time": null, "creation_time": 1724800825.073737, "location": {"id": 150074827, "name": "Southern Region", "detail": "Iceland", "full_detail": "Iceland", "country_code": "IS", "lat": 63.626726294791965, "lon": -19.436294016683092, "venue": null, "uuid": "0DC0B4FB-A763-4A3F-8306-CF7132754AC3"}, "supertype": "normal", "is_deleted": false, "open_graph_id": null, "fb_publish_status": null, "timezone_id": "Atlantic/Reykjavik", "views": 0, "comment_count": 0, "weather_condition": "partly-cloudy-day", "weather_temperature": 11.0, "uuid": "507C3BAA-F6AA-420D-83BE-69470526FC64"}, {"id": 121321244, "trip_id": 13497269, "location_id": 150075228, "main_media_item_path": null, "name": "Sundlaugin Hvolsvelli", "display_name": "Sundlaugin Hvolsvelli", "description": "Swimming at the local town pool! It had lap pool, small kiddie pool, hot tub and a slide. We didn\u2019t try the really hot tub, sauna, or polar plunge. \n\n*aerial pic stolen from the internet", "slug": "hvolsvollur", "display_slug": "hvolsvollur", "type": 1, "start_time": 1724752800.0, "end_time": null, "creation_time": 1724801943.255424, "location": {"id": 150075228, "name": "Hvolsvollur", "detail": "Iceland", "full_detail": "South, Iceland", "country_code": "IS", "lat": 63.75307415864169, "lon": -20.220233454395355, "venue": null, "uuid": "E9BA2B54-FEEB-4835-85C2-A53F219F97A9"}, "supertype": "normal", "is_deleted": false, "open_graph_id": null, "fb_publish_status": null, "timezone_id": "Atlantic/Reykjavik", "views": 0, "comment_count": 0, "weather_condition": "rain", "weather_temperature": 11.0, "uuid": "7C730D09-E0FC-4C0B-9CC4-5F472879BB49"}, {"id": 121321377, "trip_id": 13497269, "location_id": 150075391, "main_media_item_path": null, "name": "Yarn shopping", "display_name": "Yarn shopping", "description": "The yarn shops are so cool here! One we went to the raise and sheer their own sheep (twice a year), mill and dye the yarn, and then sell it upstairs.", "slug": "southern-region", "display_slug": "southern-region", "type": 1, "start_time": 1724772600.0, "end_time": null, "creation_time": 1724802130.331212, "location": {"id": 150075391, "name": "Southern Region", "detail": "Iceland", "full_detail": "Iceland", "country_code": "IS", "lat": 63.88824323336676, "lon": -20.859763200636422, "venue": null, "uuid": "DAEF2A80-AA92-4BE6-8FCA-830DE009E014"}, "supertype": "normal", "is_deleted": false, "open_graph_id": null, "fb_publish_status": null, "timezone_id": "Atlantic/Reykjavik", "views": 0, "comment_count": 0, "weather_condition": "rain", "weather_temperature": 13.0, "uuid": "125E3353-C25B-4E88-9042-955511D483A2"}, {"id": 121379643, "trip_id": 13497269, "location_id": 150148942, "main_media_item_path": null, "name": "Ommubaer (Grandma's House)", "display_name": "Ommubaer (Grandma's House)", "description": "Our airbnb for the last portion of our Iceland trip was at Grandma's House (Ommubaer). One of the first houses built in 1942. Our host, Haraldur, was extremely friendly and loved telling us about the history of the area, the house, and his family.", "slug": "hvolsvollur", "display_slug": "hvolsvollur", "type": 1, "start_time": 1724828400.0, "end_time": null, "creation_time": 1724802192.665515, "location": {"id": 150148942, "name": "Hvolsvollur", "detail": "Iceland", "full_detail": "South, Iceland", "country_code": "IS", "lat": 63.75202421406789, "lon": -20.21873876884996, "venue": null, "uuid": "DE1C2BF9-D8F7-4F6A-AA53-FFE41941A2F0"}, "supertype": "normal", "is_deleted": false, "open_graph_id": null, "fb_publish_status": null, "timezone_id": "Atlantic/Reykjavik", "views": 0, "comment_count": 0, "weather_condition": "rain", "weather_temperature": 12.0, "uuid": "11F4EE1A-D0CD-4B67-9234-EB8489B0A3B7"}, {"id": 121381558, "trip_id": 13497269, "location_id": 150151312, "main_media_item_path": null, "name": "Sundhn\u00faksg\u00edgar Volcano", "display_name": "Sundhn\u00faksg\u00edgar Volcano", "description": "On the way to the airport, the smoke from the volcano got thicker. Then we could see lava spluttering out. Crazy cool!", "slug": "grindavik", "display_slug": "grindavik", "type": 1, "start_time": 1724834400.0, "end_time": null, "creation_time": 1724846304.365932, "location": {"id": 150151312, "name": "Grindav\u00edk", "detail": "Iceland", "full_detail": "Grindav\u00edk, Iceland", "country_code": "IS", "lat": 63.89837861450631, "lon": -22.38070543740392, "venue": null, "uuid": "AD69967A-55C0-4411-B74F-3236F4F7FF72"}, "supertype": "normal", "is_deleted": false, "open_graph_id": null, "fb_publish_status": null, "timezone_id": "Atlantic/Reykjavik", "views": 0, "comment_count": 0, "weather_condition": "partly-cloudy-day", "weather_temperature": 11.0, "uuid": "11BA34A7-F8BE-4C82-B1C5-F23DED6D4F2E"}, {"id": 121381849, "trip_id": 13497269, "location_id": 150151653, "main_media_item_path": null, "name": "KEF airport ", "display_name": "KEF airport ", "description": "Sad to say goodbye to Robbie for the next 3 months. Peace out Iceland! Hope to adventure here again soon!", "slug": "njardvik", "display_slug": "njardvik", "type": 1, "start_time": 1724872799.5, "end_time": null, "creation_time": 1724846419.59093, "location": {"id": 150151653, "name": "Njardvik", "detail": "Iceland", "full_detail": "Southern Peninsula, Iceland", "country_code": "IS", "lat": 63.98157630005466, "lon": -22.613447064917807, "venue": null, "uuid": "CDA946B7-1BCD-473A-9FB6-26DAFFDEEE54"}, "supertype": "normal", "is_deleted": false, "open_graph_id": null, "fb_publish_status": null, "timezone_id": "Atlantic/Reykjavik", "views": 0, "comment_count": 0, "weather_condition": "partly-cloudy-day", "weather_temperature": 12.0, "uuid": "2E438B21-80C7-400D-8C24-6A322AF3B2FF"}]}